CoolPlot/__init__.py
CoolPlot/__version__.py
CoolPlot/core.py
CoolPlot/helpers.py
CoolPlot/Calc/__init__.py
CoolPlot/Plot/Common.py
CoolPlot/Plot/ConsistencyPlots.py
CoolPlot/Plot/Plots.py
CoolPlot/Plot/PsychChart.py
CoolPlot/Plot/PsychScript.py
CoolPlot/Plot/SimpleCycles.py
CoolPlot/Plot/SimpleCyclesCompression.py
CoolPlot/Plot/SimpleCyclesExpansion.py
CoolPlot/Plot/Tests.py
CoolPlot/Plot/__init__.py
CoolPlot/Plot/psy.py
CoolPlot/Util/EnhancedState.py
CoolPlot/Util/Quantities.py
CoolPlot/Util/Units.py
CoolPlot/Util/__init__.py
CoolPlot-0.1.6.dist-info/LICENSE
CoolPlot-0.1.6.dist-info/METADATA
CoolPlot-0.1.6.dist-info/WHEEL
CoolPlot-0.1.6.dist-info/top_level.txt
CoolPlot-0.1.6.dist-info/RECORD
