Metadata-Version: 2.1
Name: CoolPlot
Version: 0.1.6
Summary: Create property plots for engineering thermodynamics using CoolProp as data source.
Home-page: https://github.com/CoolProp/CoolPlot
Author: Jorrit Wronski
Author-email: coolplot@jorrit.org
License: MIT
Platform: UNKNOWN
Classifier: License :: OSI Approved :: MIT License
Classifier: Programming Language :: Python
Classifier: Programming Language :: Python :: 3
Classifier: Programming Language :: Python :: 3.6
Classifier: Programming Language :: Python :: Implementation :: CPython
Classifier: Programming Language :: Python :: Implementation :: PyPy
Requires-Python: >=3.6.0
Requires-Dist: numpy
Requires-Dist: matplotlib
Requires-Dist: coolprop
